{
  "version": "1.0",
  "description": "AutoMate Vehicle Capability Catalog. The agent uses this dictionary to drive intent classification, slot extraction, tool selection, and safety decisions. match_keywords and priority are compact (whitespace-free) matching hints.",
  "capabilities": [
    {
      "capability_id": "climate.warmer",
      "category": "climate",
      "intent": "CONTROL_CLIMATE",
      "tool_name": "setClimate",
      "display_name": "실내 온도 올리기",
      "description": "실내가 춥거나 사용자가 따뜻함을 원할 때 난방을 켜고 온도를 올린다.",
      "example_utterances": ["나 좀 추워", "손시려워", "발 시려워", "몸이 추워", "따뜻하게 해줘", "히터 켜줘"],
      "match_keywords": ["추워", "춥", "손시려", "손시렵", "발시려", "발시렵", "시려워", "몸이추", "따뜻하게", "히터", "난방", "온도올", "온도높"],
      "priority": 65,
      "confidence": 0.92,
      "required_slots": [],
      "optional_slots": ["temperature"],
      "default_arguments": { "mode": "heating", "temperature": 24, "target_temperature": 24, "temperature_preference": "warmer" },
      "allowed_while_driving": true,
      "risk_level": "low",
      "state_updates": { "air_conditioner_status": "heating" },
      "success_response_template": "{message}",
      "clarification_question": null,
      "blocked_response": null
    },
    {
      "capability_id": "climate.cooler",
      "category": "climate",
      "intent": "CONTROL_CLIMATE",
      "tool_name": "setClimate",
      "display_name": "실내 온도 내리기",
      "description": "실내가 덥거나 사용자가 시원함을 원할 때 냉방을 켜고 온도를 내린다.",
      "example_utterances": ["너무 더워", "덥다", "시원하게 해줘", "에어컨 켜줘"],
      "match_keywords": ["더워", "덥다", "더움", "시원하게", "에어컨", "온도내", "온도낮", "쿨러"],
      "priority": 65,
      "confidence": 0.92,
      "required_slots": [],
      "optional_slots": ["temperature"],
      "default_arguments": { "mode": "cooling", "temperature": 20, "target_temperature": 20, "temperature_preference": "cooler" },
      "allowed_while_driving": true,
      "risk_level": "low",
      "state_updates": { "air_conditioner_status": "cooling" },
      "success_response_template": "{message}",
      "clarification_question": null,
      "blocked_response": null
    },
    {
      "capability_id": "climate.fresh_air",
      "category": "climate",
      "intent": "CONTROL_CLIMATE",
      "tool_name": "setClimate",
      "display_name": "환기",
      "description": "실내 공기가 답답할 때 외기를 유입해 환기한다.",
      "example_utterances": ["차 안이 답답해", "환기 좀 해줘", "공기가 안 좋아"],
      "match_keywords": ["답답", "환기", "공기바꿔", "공기좀", "공기안좋", "숨막"],
      "priority": 64,
      "confidence": 0.91,
      "required_slots": [],
      "optional_slots": [],
      "default_arguments": { "mode": "fresh_air", "temperature": 22, "target_temperature": 22 },
      "allowed_while_driving": true,
      "risk_level": "low",
      "state_updates": { "air_conditioner_status": "fresh_air" },
      "success_response_template": "{message}",
      "clarification_question": null,
      "blocked_response": null
    },
    {
      "capability_id": "climate.recirculation",
      "category": "climate",
      "intent": "CONTROL_CLIMATE",
      "tool_name": "setClimate",
      "display_name": "내기 순환",
      "description": "외부 냄새가 들어올 때 내기 순환 모드로 전환하고 필요 시 창문을 닫는다.",
      "example_utterances": ["밖에서 소똥냄새나", "밖에서 냄새나", "악취가 들어와"],
      "match_keywords": ["소똥냄새", "냄새나", "냄새들어", "냄새들어와", "악취", "냄새", "내기순환"],
      "priority": 66,
      "confidence": 0.94,
      "required_slots": [],
      "optional_slots": ["close_window"],
      "default_arguments": { "mode": "recirculation", "temperature": 22, "target_temperature": 22 },
      "allowed_while_driving": true,
      "risk_level": "low",
      "state_updates": { "air_conditioner_status": "recirculation" },
      "success_response_template": "{message}",
      "clarification_question": null,
      "blocked_response": null
    },
    {
      "capability_id": "climate.defrost",
      "category": "climate",
      "intent": "CONTROL_CLIMATE",
      "tool_name": "setClimate",
      "display_name": "앞유리 성에 제거",
      "description": "앞유리에 김이 서리거나 성에가 낄 때 제거한다.",
      "example_utterances": ["앞유리에 김서려", "성에 제거해줘", "앞유리 서리 없애줘"],
      "match_keywords": ["성에", "김서림", "김서려", "앞유리", "서리", "디포그", "성에제거"],
      "priority": 63,
      "confidence": 0.92,
      "required_slots": [],
      "optional_slots": [],
      "default_arguments": { "mode": "defrost", "temperature": 24, "target_temperature": 24 },
      "allowed_while_driving": true,
      "risk_level": "low",
      "state_updates": { "air_conditioner_status": "defrost" },
      "success_response_template": "{message}",
      "clarification_question": null,
      "blocked_response": null
    },
    {
      "capability_id": "navigation.home",
      "category": "navigation",
      "intent": "SET_NAVIGATION",
      "tool_name": "setNavigation",
      "display_name": "집 안내",
      "description": "집으로 경로를 안내한다.",
      "example_utterances": ["집으로 안내해줘", "집에 가자", "집으로 가줘"],
      "match_keywords": ["집으로", "집안내", "집에가", "집으로가", "집까지", "집으로안내"],
      "priority": 92,
      "confidence": 0.94,
      "required_slots": ["destination"],
      "optional_slots": ["route_type"],
      "default_arguments": { "destination": "home", "route_type": "fastest" },
      "allowed_while_driving": true,
      "risk_level": "low",
      "state_updates": {},
      "success_response_template": "{message}",
      "clarification_question": null,
      "blocked_response": null
    },
    {
      "capability_id": "navigation.company",
      "category": "navigation",
      "intent": "SET_NAVIGATION",
      "tool_name": "setNavigation",
      "display_name": "회사 안내",
      "description": "회사로 경로를 안내한다.",
      "example_utterances": ["회사로 안내해줘", "회사로 가자", "회사까지 안내해줘"],
      "match_keywords": ["회사로", "회사안내", "회사가", "회사까지", "회사로가", "회사로안내"],
      "priority": 92,
      "confidence": 0.94,
      "required_slots": ["destination"],
      "optional_slots": ["route_type"],
      "default_arguments": { "destination": "company", "route_type": "fastest" },
      "allowed_while_driving": true,
      "risk_level": "low",
      "state_updates": {},
      "success_response_template": "{message}",
      "clarification_question": null,
      "blocked_response": null
    },
    {
      "capability_id": "navigation.eta",
      "category": "navigation",
      "intent": "SET_NAVIGATION",
      "tool_name": "setNavigation",
      "display_name": "예상 소요 시간 확인",
      "description": "특정 목적지까지의 예상 소요 시간을 안내하며 경로를 설정한다.",
      "example_utterances": ["서울역까지 얼마나 걸려", "대전역까지 얼마나 걸려", "도착 시간 알려줘"],
      "match_keywords": ["얼마나걸려", "얼마나걸림", "얼마나걸리", "소요시간", "도착시간", "몇분걸려"],
      "priority": 91,
      "confidence": 0.93,
      "required_slots": ["destination"],
      "optional_slots": ["route_type"],
      "default_arguments": { "route_type": "fastest" },
      "allowed_while_driving": true,
      "risk_level": "low",
      "state_updates": {},
      "success_response_template": "{message}",
      "clarification_question": "어느 목적지까지의 소요 시간을 알려드릴까요?",
      "blocked_response": null
    },
    {
      "capability_id": "navigation.general",
      "category": "navigation",
      "intent": "SET_NAVIGATION",
      "tool_name": "setNavigation",
      "display_name": "일반 목적지 안내",
      "description": "사용자가 말한 목적지로 경로를 안내한다. 목적지가 없으면 재질문한다.",
      "example_utterances": ["서울역으로 가고싶어", "성심당으로 가줘", "부산역 가자", "길 안내해줘"],
      "match_keywords": ["가고싶", "까지안내", "까지길안내", "안내해줘", "길안내", "네비", "내비", "경로안내", "목적지설정", "가자", "가줘", "까지"],
      "priority": 90,
      "confidence": 0.91,
      "required_slots": ["destination"],
      "optional_slots": ["route_type"],
      "default_arguments": { "route_type": "fastest" },
      "allowed_while_driving": true,
      "risk_level": "low",
      "state_updates": {},
      "success_response_template": "{message}",
      "clarification_question": "어디로 안내해 드릴까요? 집, 회사, 또는 목적지를 말씀해 주세요.",
      "blocked_response": null
    },
    {
      "capability_id": "navigation.clarification",
      "category": "navigation",
      "intent": "SET_NAVIGATION",
      "tool_name": "setNavigation",
      "display_name": "목적지 누락 시 재질문",
      "description": "목적지가 없는 안내 요청 시 재질문을 담당하는 문서용 정의. 실제로는 navigation.general의 required_slots 누락으로 처리된다.",
      "example_utterances": ["안내해줘", "길 안내해줘"],
      "match_keywords": [],
      "priority": 89,
      "confidence": 0.9,
      "required_slots": ["destination"],
      "optional_slots": [],
      "default_arguments": { "route_type": "fastest" },
      "allowed_while_driving": true,
      "risk_level": "none",
      "state_updates": {},
      "success_response_template": "{message}",
      "clarification_question": "어디로 안내해 드릴까요? 집, 회사, 또는 목적지를 말씀해 주세요.",
      "blocked_response": null
    },
    {
      "capability_id": "media.calm",
      "category": "media",
      "intent": "PLAY_MEDIA",
      "tool_name": "playMedia",
      "display_name": "조용한 음악 재생",
      "description": "잔잔하고 조용한 음악을 재생한다.",
      "example_utterances": ["조용한 음악 틀어줘", "잔잔한 노래 틀어줘"],
      "match_keywords": ["조용한노래", "잔잔한음악", "조용한음악", "잔잔한노래", "조용한거", "잔잔한거"],
      "priority": 51,
      "confidence": 0.93,
      "required_slots": [],
      "optional_slots": [],
      "default_arguments": { "mood": "calm", "genre": "calm", "volume": "low", "action": "play" },
      "allowed_while_driving": true,
      "risk_level": "low",
      "state_updates": { "media_status": "playing" },
      "success_response_template": "{message}",
      "clarification_question": null,
      "blocked_response": null
    },
    {
      "capability_id": "media.energetic",
      "category": "media",
      "intent": "PLAY_MEDIA",
      "tool_name": "playMedia",
      "display_name": "신나는 음악 재생",
      "description": "신나고 활기찬 음악을 재생한다.",
      "example_utterances": ["신나는 음악 틀어줘", "빠른 음악 틀어줘"],
      "match_keywords": ["신나는노래", "신나는음악", "신나는거", "빠른음악", "신나는걸"],
      "priority": 51,
      "confidence": 0.93,
      "required_slots": [],
      "optional_slots": [],
      "default_arguments": { "mood": "energetic", "genre": "energetic", "volume": "medium", "action": "play" },
      "allowed_while_driving": true,
      "risk_level": "low",
      "state_updates": { "media_status": "playing" },
      "success_response_template": "{message}",
      "clarification_question": null,
      "blocked_response": null
    },
    {
      "capability_id": "media.stop",
      "category": "media",
      "intent": "PLAY_MEDIA",
      "tool_name": "playMedia",
      "display_name": "음악 정지",
      "description": "재생 중인 음악을 정지한다.",
      "example_utterances": ["음악 꺼줘", "노래 정지", "음악 멈춰"],
      "match_keywords": ["노래꺼", "음악꺼", "노래끄", "음악끄", "재생중지", "음악중지", "노래중지", "음악멈", "노래멈", "음악정지", "노래정지"],
      "priority": 52,
      "confidence": 0.93,
      "required_slots": [],
      "optional_slots": [],
      "default_arguments": { "action": "stop", "genre": "default" },
      "allowed_while_driving": true,
      "risk_level": "low",
      "state_updates": { "media_status": "off" },
      "success_response_template": "{message}",
      "clarification_question": null,
      "blocked_response": null
    },
    {
      "capability_id": "media.play",
      "category": "media",
      "intent": "PLAY_MEDIA",
      "tool_name": "playMedia",
      "display_name": "음악 재생",
      "description": "일반 음악을 재생한다.",
      "example_utterances": ["음악 틀어줘", "노래 재생해줘", "플레이리스트 틀어줘"],
      "match_keywords": ["노래", "음악", "틀어", "재생", "플레이", "플레이리스트"],
      "priority": 49,
      "confidence": 0.9,
      "required_slots": [],
      "optional_slots": [],
      "default_arguments": { "mood": "default", "genre": "default", "volume": "medium", "action": "play" },
      "allowed_while_driving": true,
      "risk_level": "low",
      "state_updates": { "media_status": "playing" },
      "success_response_template": "{message}",
      "clarification_question": null,
      "blocked_response": null
    },
    {
      "capability_id": "media.volume_down",
      "category": "media",
      "intent": "CHANGE_VEHICLE_SETTING",
      "tool_name": "changeVehicleSetting",
      "display_name": "볼륨 낮추기",
      "description": "미디어 볼륨을 낮춘다.",
      "example_utterances": ["소리 줄여줘", "볼륨 낮춰줘", "소리 작게"],
      "match_keywords": ["소리줄", "볼륨낮", "볼륨줄", "소리낮", "음악소리줄", "소리작게", "볼륨다운"],
      "priority": 88,
      "confidence": 0.95,
      "required_slots": [],
      "optional_slots": [],
      "default_arguments": { "setting": "volume", "value": "down" },
      "allowed_while_driving": true,
      "risk_level": "low",
      "state_updates": {},
      "success_response_template": "{message}",
      "clarification_question": null,
      "blocked_response": null
    },
    {
      "capability_id": "media.volume_up",
      "category": "media",
      "intent": "CHANGE_VEHICLE_SETTING",
      "tool_name": "changeVehicleSetting",
      "display_name": "볼륨 올리기",
      "description": "미디어 볼륨을 올린다.",
      "example_utterances": ["소리 키워줘", "볼륨 올려줘", "소리 크게"],
      "match_keywords": ["소리키", "볼륨키", "볼륨올", "음악소리키", "소리크게", "볼륨업", "소리높"],
      "priority": 88,
      "confidence": 0.95,
      "required_slots": [],
      "optional_slots": [],
      "default_arguments": { "setting": "volume", "value": "up" },
      "allowed_while_driving": true,
      "risk_level": "low",
      "state_updates": {},
      "success_response_template": "{message}",
      "clarification_question": null,
      "blocked_response": null
    },
    {
      "capability_id": "phone.mother",
      "category": "phone",
      "intent": "MAKE_CALL",
      "tool_name": "makeCall",
      "display_name": "엄마 전화",
      "description": "엄마에게 핸즈프리로 전화를 건다.",
      "example_utterances": ["엄마한테 전화해줘", "엄마한테 전화 걸어줘"],
      "match_keywords": ["엄마"],
      "priority": 96,
      "confidence": 0.95,
      "required_slots": ["contact"],
      "optional_slots": [],
      "default_arguments": { "contact": "mother", "hands_free": true, "action": "call" },
      "allowed_while_driving": true,
      "risk_level": "low",
      "state_updates": { "media_status": "paused" },
      "success_response_template": "{message}",
      "clarification_question": null,
      "blocked_response": null
    },
    {
      "capability_id": "phone.father",
      "category": "phone",
      "intent": "MAKE_CALL",
      "tool_name": "makeCall",
      "display_name": "아빠 전화",
      "description": "아빠에게 핸즈프리로 전화를 건다.",
      "example_utterances": ["아빠한테 전화해줘", "아빠한테 전화 걸어줘"],
      "match_keywords": ["아빠"],
      "priority": 96,
      "confidence": 0.95,
      "required_slots": ["contact"],
      "optional_slots": [],
      "default_arguments": { "contact": "father", "hands_free": true, "action": "call" },
      "allowed_while_driving": true,
      "risk_level": "low",
      "state_updates": { "media_status": "paused" },
      "success_response_template": "{message}",
      "clarification_question": null,
      "blocked_response": null
    },
    {
      "capability_id": "phone.general",
      "category": "phone",
      "intent": "MAKE_CALL",
      "tool_name": "makeCall",
      "display_name": "일반 연락처 전화",
      "description": "지정한 연락처로 핸즈프리 전화를 건다. 연락처가 없으면 재질문한다.",
      "example_utterances": ["정예진한테 전화해줘", "전화해줘"],
      "match_keywords": ["전화해", "전화좀", "전화걸", "통화해", "통화연결", "한테전화", "에게전화", "전화연결"],
      "priority": 95,
      "confidence": 0.93,
      "required_slots": ["contact"],
      "optional_slots": [],
      "default_arguments": { "hands_free": true, "action": "call" },
      "allowed_while_driving": true,
      "risk_level": "low",
      "state_updates": { "media_status": "paused" },
      "success_response_template": "{message}",
      "clarification_question": "누구에게 전화를 연결해 드릴까요? 연락처 이름을 말씀해 주세요.",
      "blocked_response": null
    },
    {
      "capability_id": "setting.window_close",
      "category": "vehicle_setting",
      "intent": "CHANGE_VEHICLE_SETTING",
      "tool_name": "changeVehicleSetting",
      "display_name": "창문 닫기",
      "description": "창문을 닫는다. 주행 중에도 허용된다.",
      "example_utterances": ["창문 닫아줘", "창 닫아줘"],
      "match_keywords": ["창문닫", "창닫", "창문좀닫", "윈도우닫"],
      "priority": 86,
      "confidence": 0.94,
      "required_slots": [],
      "optional_slots": [],
      "default_arguments": { "setting": "window_status", "value": "closed", "action": "close", "target": "window" },
      "allowed_while_driving": true,
      "risk_level": "low",
      "state_updates": { "window_status": "closed" },
      "success_response_template": "{message}",
      "clarification_question": null,
      "blocked_response": null
    },
    {
      "capability_id": "setting.window_open",
      "category": "vehicle_setting",
      "intent": "CHANGE_VEHICLE_SETTING",
      "tool_name": "changeVehicleSetting",
      "display_name": "창문 열기",
      "description": "창문을 연다. 주행 중에는 안전을 위해 차단된다.",
      "example_utterances": ["창문 열어줘", "창 열어줘"],
      "match_keywords": ["창문열", "창열", "창문좀열", "윈도우열"],
      "priority": 86,
      "confidence": 0.94,
      "required_slots": [],
      "optional_slots": [],
      "default_arguments": { "setting": "window_status", "value": "open", "action": "open", "target": "window" },
      "allowed_while_driving": false,
      "risk_level": "critical",
      "state_updates": { "window_status": "open" },
      "success_response_template": "{message}",
      "clarification_question": null,
      "blocked_response": "주행 중에는 창문 열기와 같은 위험한 제어를 수행할 수 없습니다. 정차 후 다시 요청해 주세요."
    },
    {
      "capability_id": "setting.wiper_auto",
      "category": "vehicle_setting",
      "intent": "CHANGE_VEHICLE_SETTING",
      "tool_name": "changeVehicleSetting",
      "display_name": "와이퍼 자동",
      "description": "와이퍼를 자동 모드로 설정한다.",
      "example_utterances": ["비 오니까 와이퍼 자동으로 해줘", "와이퍼 자동으로 해줘"],
      "match_keywords": ["와이퍼자동", "와이퍼오토", "비오니까와이퍼", "와이퍼auto"],
      "priority": 85,
      "confidence": 0.93,
      "required_slots": [],
      "optional_slots": [],
      "default_arguments": { "setting": "wiper_mode", "value": "auto", "action": "auto", "target": "wiper" },
      "allowed_while_driving": true,
      "risk_level": "low",
      "state_updates": {},
      "success_response_template": "{message}",
      "clarification_question": null,
      "blocked_response": null
    },
    {
      "capability_id": "setting.wiper_on",
      "category": "vehicle_setting",
      "intent": "CHANGE_VEHICLE_SETTING",
      "tool_name": "changeVehicleSetting",
      "display_name": "와이퍼 켜기",
      "description": "와이퍼를 작동시킨다.",
      "example_utterances": ["와이퍼 켜줘", "비 와서 와이퍼 켜줘", "와이퍼 작동해줘"],
      "match_keywords": ["와이퍼켜", "와이퍼틀", "와이퍼on", "와이퍼작동", "와이퍼"],
      "priority": 84,
      "confidence": 0.92,
      "required_slots": [],
      "optional_slots": [],
      "default_arguments": { "setting": "wiper_status", "value": "on", "action": "on", "target": "wiper" },
      "allowed_while_driving": true,
      "risk_level": "low",
      "state_updates": {},
      "success_response_template": "{message}",
      "clarification_question": null,
      "blocked_response": null
    },
    {
      "capability_id": "setting.brightness_low",
      "category": "vehicle_setting",
      "intent": "CHANGE_VEHICLE_SETTING",
      "tool_name": "changeVehicleSetting",
      "display_name": "화면 밝기 낮추기",
      "description": "눈부심을 줄이기 위해 화면 밝기를 낮춘다.",
      "example_utterances": ["눈부셔", "화면이 너무 밝아", "화면 밝기 낮춰줘"],
      "match_keywords": ["눈부셔", "눈부심", "화면밝기낮", "디스플레이밝기낮", "밝기낮", "화면이너무밝", "화면너무밝", "너무밝아", "화면어둡"],
      "priority": 87,
      "confidence": 0.95,
      "required_slots": [],
      "optional_slots": [],
      "default_arguments": { "setting": "display_brightness", "value": "low" },
      "allowed_while_driving": true,
      "risk_level": "low",
      "state_updates": { "display_brightness": "low" },
      "success_response_template": "{message}",
      "clarification_question": null,
      "blocked_response": null
    },
    {
      "capability_id": "setting.door_lock",
      "category": "vehicle_setting",
      "intent": "CHANGE_VEHICLE_SETTING",
      "tool_name": "changeVehicleSetting",
      "display_name": "문 잠금",
      "description": "차량 문을 잠근다.",
      "example_utterances": ["문 잠가줘", "도어 잠가줘"],
      "match_keywords": ["문잠", "도어잠", "문좀잠", "문잠가"],
      "priority": 91,
      "confidence": 0.93,
      "required_slots": [],
      "optional_slots": [],
      "default_arguments": { "setting": "door_lock", "value": "locked" },
      "allowed_while_driving": true,
      "risk_level": "low",
      "state_updates": {},
      "success_response_template": "{message}",
      "clarification_question": null,
      "blocked_response": null
    },
    {
      "capability_id": "setting.display_complex_block",
      "category": "vehicle_setting",
      "intent": "CHANGE_VEHICLE_SETTING",
      "tool_name": "changeVehicleSetting",
      "display_name": "복잡한 화면 설정 변경 (주행 중 차단)",
      "description": "주행 중 복잡한 화면/디스플레이 설정 변경은 안전을 위해 차단한다.",
      "example_utterances": ["운전 중인데 화면 설정 좀 복잡하게 바꿔줘", "디스플레이 설정 자세히 바꿔줘"],
      "match_keywords": ["화면설정", "디스플레이설정", "설정바꿔", "설정변경", "설정좀바꿔", "복잡하게바꿔"],
      "priority": 82,
      "confidence": 0.9,
      "required_slots": [],
      "optional_slots": [],
      "default_arguments": { "setting": "display", "value": "high", "complexity": "high", "target": "display" },
      "allowed_while_driving": false,
      "risk_level": "high",
      "state_updates": {},
      "success_response_template": "{message}",
      "clarification_question": null,
      "blocked_response": "안전을 위해 정차 후 화면 설정을 도와드릴게요."
    },
    {
      "capability_id": "status.battery",
      "category": "vehicle_status",
      "intent": "CHECK_VEHICLE_STATUS",
      "tool_name": "checkVehicleStatus",
      "display_name": "배터리 확인",
      "description": "배터리 잔량을 확인한다.",
      "example_utterances": ["배터리 상태 확인해줘", "배터리 얼마나 남았어?"],
      "match_keywords": ["배터리"],
      "priority": 73,
      "confidence": 0.94,
      "required_slots": [],
      "optional_slots": [],
      "default_arguments": { "target": "battery_level" },
      "allowed_while_driving": true,
      "risk_level": "none",
      "state_updates": {},
      "success_response_template": "{message}",
      "clarification_question": null,
      "blocked_response": null
    },
    {
      "capability_id": "status.fuel",
      "category": "vehicle_status",
      "intent": "CHECK_VEHICLE_STATUS",
      "tool_name": "checkVehicleStatus",
      "display_name": "연료 확인",
      "description": "연료 잔량을 확인한다.",
      "example_utterances": ["연료 잔량 알려줘", "기름 얼마나 남았어?"],
      "match_keywords": ["연료", "기름"],
      "priority": 72,
      "confidence": 0.93,
      "required_slots": [],
      "optional_slots": [],
      "default_arguments": { "target": "fuel_level" },
      "allowed_while_driving": true,
      "risk_level": "none",
      "state_updates": {},
      "success_response_template": "{message}",
      "clarification_question": null,
      "blocked_response": null
    },
    {
      "capability_id": "status.indoor_temperature",
      "category": "vehicle_status",
      "intent": "CHECK_VEHICLE_STATUS",
      "tool_name": "checkVehicleStatus",
      "display_name": "실내 온도 확인",
      "description": "현재 실내 온도를 확인한다.",
      "example_utterances": ["실내 온도 몇 도야?", "차 안 온도 알려줘"],
      "match_keywords": ["실내온도", "실내온", "온도몇도", "몇도야", "차안온도"],
      "priority": 73,
      "confidence": 0.93,
      "required_slots": [],
      "optional_slots": [],
      "default_arguments": { "target": "indoor_temperature" },
      "allowed_while_driving": true,
      "risk_level": "none",
      "state_updates": {},
      "success_response_template": "{message}",
      "clarification_question": null,
      "blocked_response": null
    },
    {
      "capability_id": "status.weather",
      "category": "vehicle_status",
      "intent": "CHECK_VEHICLE_STATUS",
      "tool_name": "checkVehicleStatus",
      "display_name": "날씨 확인",
      "description": "현재 날씨를 확인하고 필요 시 창문 상태를 안내한다.",
      "example_utterances": ["밖에 비가 와", "지금 날씨 어때?"],
      "match_keywords": ["밖에비가", "비가와", "밖에비", "비와", "지금비", "비온다", "비오나", "날씨어때", "날씨알려", "지금날씨", "날씨좀"],
      "priority": 74,
      "confidence": 0.94,
      "required_slots": [],
      "optional_slots": [],
      "default_arguments": { "target": "weather" },
      "allowed_while_driving": true,
      "risk_level": "none",
      "state_updates": {},
      "success_response_template": "{message}",
      "clarification_question": null,
      "blocked_response": null
    },
    {
      "capability_id": "status.overall",
      "category": "vehicle_status",
      "intent": "CHECK_VEHICLE_STATUS",
      "tool_name": "checkVehicleStatus",
      "display_name": "차량 상태 요약",
      "description": "배터리, 연료, 실내 온도, 날씨 등 차량 상태를 요약한다.",
      "example_utterances": ["차 상태 알려줘", "차량 상태 확인해줘", "차 괜찮아?"],
      "match_keywords": ["차상태", "차량상태", "상태알려", "상태확인", "차괜찮"],
      "priority": 71,
      "confidence": 0.92,
      "required_slots": [],
      "optional_slots": [],
      "default_arguments": { "target": "overall" },
      "allowed_while_driving": true,
      "risk_level": "none",
      "state_updates": {},
      "success_response_template": "{message}",
      "clarification_question": null,
      "blocked_response": null
    },
    {
      "capability_id": "nearby.rest_area",
      "category": "nearby_place",
      "intent": "FIND_NEARBY_PLACE",
      "tool_name": "findNearbyPlace",
      "display_name": "휴게소 찾기",
      "description": "졸리거나 쉬고 싶을 때 가까운 휴게소를 찾는다.",
      "example_utterances": ["졸려", "쉬고 싶어", "휴게소 찾아줘"],
      "match_keywords": ["졸려", "졸리", "졸음", "피곤", "쉬고싶", "휴게소", "쉬었으면"],
      "priority": 56,
      "confidence": 0.9,
      "required_slots": [],
      "optional_slots": [],
      "default_arguments": { "place_type": "rest_area", "urgency": "high" },
      "allowed_while_driving": true,
      "risk_level": "low",
      "state_updates": {},
      "success_response_template": "{message}",
      "clarification_question": null,
      "blocked_response": null
    },
    {
      "capability_id": "nearby.gas_station",
      "category": "nearby_place",
      "intent": "FIND_NEARBY_PLACE",
      "tool_name": "findNearbyPlace",
      "display_name": "주유소 찾기",
      "description": "가까운 주유소를 찾는다.",
      "example_utterances": ["가까운 주유소 찾아줘", "주유소 어디 있어?"],
      "match_keywords": ["주유소", "주유"],
      "priority": 55,
      "confidence": 0.9,
      "required_slots": [],
      "optional_slots": [],
      "default_arguments": { "place_type": "gas_station" },
      "allowed_while_driving": true,
      "risk_level": "low",
      "state_updates": {},
      "success_response_template": "{message}",
      "clarification_question": null,
      "blocked_response": null
    },
    {
      "capability_id": "nearby.charging_station",
      "category": "nearby_place",
      "intent": "FIND_NEARBY_PLACE",
      "tool_name": "findNearbyPlace",
      "display_name": "충전소 찾기",
      "description": "가까운 전기차 충전소를 찾는다.",
      "example_utterances": ["가까운 충전소 찾아줘", "충전소 어디 있어?"],
      "match_keywords": ["충전소", "충전"],
      "priority": 55,
      "confidence": 0.9,
      "required_slots": [],
      "optional_slots": [],
      "default_arguments": { "place_type": "charging_station" },
      "allowed_while_driving": true,
      "risk_level": "low",
      "state_updates": {},
      "success_response_template": "{message}",
      "clarification_question": null,
      "blocked_response": null
    },
    {
      "capability_id": "nearby.cafe",
      "category": "nearby_place",
      "intent": "FIND_NEARBY_PLACE",
      "tool_name": "findNearbyPlace",
      "display_name": "카페 찾기",
      "description": "가까운 카페를 찾는다.",
      "example_utterances": ["근처 카페 찾아줘", "커피 마시고 싶어"],
      "match_keywords": ["카페", "커피"],
      "priority": 55,
      "confidence": 0.9,
      "required_slots": [],
      "optional_slots": [],
      "default_arguments": { "place_type": "cafe" },
      "allowed_while_driving": true,
      "risk_level": "low",
      "state_updates": {},
      "success_response_template": "{message}",
      "clarification_question": null,
      "blocked_response": null
    },
    {
      "capability_id": "schedule.today",
      "category": "schedule",
      "intent": "READ_SCHEDULE",
      "tool_name": "readSchedule",
      "display_name": "오늘 일정 확인",
      "description": "오늘 일정을 확인한다.",
      "example_utterances": ["오늘 일정 알려줘", "오늘 스케줄 뭐 있어?"],
      "match_keywords": ["일정", "스케줄", "캘린더", "약속"],
      "priority": 45,
      "confidence": 0.9,
      "required_slots": [],
      "optional_slots": [],
      "default_arguments": { "range": "today" },
      "allowed_while_driving": true,
      "risk_level": "none",
      "state_updates": {},
      "success_response_template": "{message}",
      "clarification_question": null,
      "blocked_response": null
    }
  ]
}
